shipdan_model/__init__.py
shipdan_model/manage.py
shipdan_model/shipdan_apps/__init__.py
shipdan_model/shipdan_apps/accounts/__init__.py
shipdan_model/shipdan_apps/accounts/admin.py
shipdan_model/shipdan_apps/accounts/apps.py
shipdan_model/shipdan_apps/accounts/models.py
shipdan_model/shipdan_apps/accounts/tests.py
shipdan_model/shipdan_apps/accounts/views.py
shipdan_model/shipdan_apps/accounts/migrations/__init__.py
shipdan_model/shipdan_apps/aligo/__init__.py
shipdan_model/shipdan_apps/aligo/admin.py
shipdan_model/shipdan_apps/aligo/apps.py
shipdan_model/shipdan_apps/aligo/models.py
shipdan_model/shipdan_apps/aligo/tests.py
shipdan_model/shipdan_apps/aligo/views.py
shipdan_model/shipdan_apps/aligo/migrations/__init__.py
shipdan_model/shipdan_apps/core/__init__.py
shipdan_model/shipdan_apps/core/admin.py
shipdan_model/shipdan_apps/core/apps.py
shipdan_model/shipdan_apps/core/models.py
shipdan_model/shipdan_apps/core/tests.py
shipdan_model/shipdan_apps/core/views.py
shipdan_model/shipdan_apps/core/migrations/__init__.py
shipdan_model/shipdan_apps/delivery/__init__.py
shipdan_model/shipdan_apps/delivery/admin.py
shipdan_model/shipdan_apps/delivery/apps.py
shipdan_model/shipdan_apps/delivery/models.py
shipdan_model/shipdan_apps/delivery/tests.py
shipdan_model/shipdan_apps/delivery/views.py
shipdan_model/shipdan_apps/delivery/migrations/__init__.py
shipdan_model/shipdan_apps/diary/__init__.py
shipdan_model/shipdan_apps/diary/admin.py
shipdan_model/shipdan_apps/diary/apps.py
shipdan_model/shipdan_apps/diary/models.py
shipdan_model/shipdan_apps/diary/tests.py
shipdan_model/shipdan_apps/diary/views.py
shipdan_model/shipdan_apps/diary/migrations/__init__.py
shipdan_model/shipdan_apps/diet/__init__.py
shipdan_model/shipdan_apps/diet/admin.py
shipdan_model/shipdan_apps/diet/apps.py
shipdan_model/shipdan_apps/diet/models.py
shipdan_model/shipdan_apps/diet/tests.py
shipdan_model/shipdan_apps/diet/views.py
shipdan_model/shipdan_apps/diet/migrations/__init__.py
shipdan_model_test2-3.6.1.dist-info/LICENSE.rst
shipdan_model_test2-3.6.1.dist-info/METADATA
shipdan_model_test2-3.6.1.dist-info/WHEEL
shipdan_model_test2-3.6.1.dist-info/top_level.txt
shipdan_model_test2-3.6.1.dist-info/RECORD
