Metadata-Version: 2.1
Name: shipdan-model-test2
Version: 3.6.1
Summary: model package for shipdan business written by Bunkerkids Tech
Home-page: https://github.com/bunkerkids/shipdan_model
Author: bunkerkids
Author-email: development@bunkerkids.net
License-File: LICENSE.rst
Requires-Dist: django
